djflow-0.2.0.dist-info/DESCRIPTION.rst
djflow-0.2.0.dist-info/WHEEL
djflow-0.2.0.dist-info/METADATA
djflow-0.2.0.dist-info/RECORD
djflow-0.2.0.dist-info/top_level.txt
djflow-0.2.0.dist-info/metadata.json
goflow/__init__.py
goflow/urls.py
djflow/__init__.py
djflow/urls.py
