Metadata-Version: 2.0
Name: djflow
Version: 0.2.0
Summary: Workflow for Django
Home-page: https://github.com/glasslion/djflow
Author: Leo Zhou
Author-email: glasslion@gmail.com
License: BSD
Keywords: djflow
Platform: UNKNOWN
Classifier: Development Status :: 3 - Alpha
Classifier: Framework :: Django
Classifier: Intended Audience :: Developers
Classifier: License :: OSI Approved :: BSD License
Classifier: Natural Language :: English
Classifier: Programming Language :: Python :: 2
Classifier: Programming Language :: Python :: 2.7
Classifier: Programming Language :: Python :: 3
Classifier: Programming Language :: Python :: 3.3
Classifier: Programming Language :: Python :: 3.4
